doksan/__init__.py
doksan/doksan.py
doksan/variables.py
doksan-0.2.2.dist-info/LICENSE
doksan-0.2.2.dist-info/METADATA
doksan-0.2.2.dist-info/WHEEL
doksan-0.2.2.dist-info/entry_points.txt
doksan-0.2.2.dist-info/top_level.txt
doksan-0.2.2.dist-info/RECORD
