Metadata-Version: 2.1
Name: doksan
Version: 0.2.2
Summary: Get soccer results and fixtures like a hacker.
Home-page: https://github.com/malisit/doksan
Author: Muhammed Sit
Author-email: masit@outlook.com
License: MIT
Classifier: License :: OSI Approved :: MIT License
Classifier: Programming Language :: Python :: 3
Classifier: Programming Language :: Python :: 3.7
License-File: LICENSE
Requires-Dist: bs4
